<?xml version="1.0" encoding="UTF-8"?>
<Root>
  <add key="Comment" value="01:「&gt;」+空白二回以上の空白を取る&#xD;&#xA;02:「&gt;」の繰り返しをまとめる&#xD;&#xA;03:二つ以上の空白を除去&#xD;&#xA;04:3~99の連続改行をまとめる&#xD;&#xA;05:3~99の連続「&gt;」+改行をまとめる&#xD;&#xA;06:先頭「&gt;」+1文字の改行を抜く"/>
  <add key="Check01" value="True"/>
  <add key="Check02" value="True"/>
  <add key="Check03" value="True"/>
  <add key="Check04" value="True"/>
  <add key="Check05" value="True"/>
  <add key="Check06" value="True"/>
  <add key="Check07" value="False"/>
  <add key="Check08" value="False"/>
  <add key="Check09" value="False"/>
  <add key="Check10" value="False"/>
  <add key="Check11" value="False"/>
  <add key="Check12" value="False"/>
  <add key="Check13" value="False"/>
  <add key="Check14" value="False"/>
  <add key="Check15" value="False"/>
  <add key="Check16" value="False"/>
  <add key="Check17" value="False"/>
  <add key="Check18" value="False"/>
  <add key="Check19" value="False"/>
  <add key="Check20" value="False"/>
  <add key="Search01" value="&gt; +(.*)"/>
  <add key="Search02" value="&gt;+"/>
  <add key="Search03" value=" +"/>
  <add key="Search04" value="(\n){3,99}"/>
  <add key="Search05" value="(\n&gt;){3,99}"/>
  <add key="Search06" value="\n&gt;(.)\n"/>
  <add key="Search07" value=""/>
  <add key="Search08" value=""/>
  <add key="Search09" value=""/>
  <add key="Search10" value=""/>
  <add key="Search11" value=""/>
  <add key="Search12" value=""/>
  <add key="Search13" value=""/>
  <add key="Search14" value=""/>
  <add key="Search15" value=""/>
  <add key="Search16" value=""/>
  <add key="Search17" value=""/>
  <add key="Search18" value=""/>
  <add key="Search19" value=""/>
  <add key="Search20" value=""/>
  <add key="Replace01" value="&gt;$1"/>
  <add key="Replace02" value="&gt;"/>
  <add key="Replace03" value=""/>
  <add key="Replace04" value="$1"/>
  <add key="Replace05" value="$1"/>
  <add key="Replace06" value="$1"/>
  <add key="Replace07" value=""/>
  <add key="Replace08" value=""/>
  <add key="Replace09" value=""/>
  <add key="Replace10" value=""/>
  <add key="Replace11" value=""/>
  <add key="Replace12" value=""/>
  <add key="Replace13" value=""/>
  <add key="Replace14" value=""/>
  <add key="Replace15" value=""/>
  <add key="Replace16" value=""/>
  <add key="Replace17" value=""/>
  <add key="Replace18" value=""/>
  <add key="Replace19" value=""/>
  <add key="Replace20" value=""/>
</Root>
